aioapollo/__init__.py
aioapollo-0.0.2.dist-info/METADATA
aioapollo-0.0.2.dist-info/WHEEL
aioapollo-0.0.2.dist-info/top_level.txt
aioapollo-0.0.2.dist-info/RECORD
